pamic-0.2.2.data/scripts/pamic
pamicg/__init__.py
pamicg/__main__.py
pamicg/app.py
pamicg/gui.py
pamicg/pamic
pamicg/pamicg.glade
pamicg/img/vintage-microphone.png
pamic-0.2.2.dist-info/LICENSE
pamic-0.2.2.dist-info/METADATA
pamic-0.2.2.dist-info/WHEEL
pamic-0.2.2.dist-info/entry_points.txt
pamic-0.2.2.dist-info/top_level.txt
pamic-0.2.2.dist-info/RECORD
