Metadata-Version: 2.1
Name: pamic
Version: 0.2.2
Summary: Funking up Pulseaudio microphone use
Home-page: https://gitlab.com/ebardie/pamic
Author: Jonathan Sambrook
Author-email: ebardie@gmail.com
License: UNKNOWN
Keywords: PulseAudio,Microphone,Echo Cancellation,Noise Supression
Platform: UNKNOWN
Classifier: License :: OSI Approved :: GNU General Public License v3 or later (GPLv3+)
Classifier: Programming Language :: Python :: 3
Classifier: Development Status :: 3 - Alpha
Classifier: Environment :: X11 Applications :: GTK
Classifier: Intended Audience :: End Users/Desktop
Classifier: Operating System :: POSIX :: Linux
Classifier: Topic :: Multimedia :: Sound/Audio
Classifier: Topic :: Multimedia :: Sound/Audio :: Capture/Recording
Requires-Python: >=3.7
Requires-Dist: psutil
